tinyecs/__init__.py
tinyecs/components.py
tinyecs/compsys.py
tinyecs/demo.py
tinyecs/tutorial.py
tinyecs/demos/__init__.py
tinyecs/demos/background.py
tinyecs/demos/bouncing_sprites.py
tinyecs/demos/example.py
tinyecs/demos/homing-missiles.py
tinyecs/demos/marquee.py
tinyecs-0.2.10.dist-info/licenses/LICENSE
tinyecs-0.2.10.dist-info/METADATA
tinyecs-0.2.10.dist-info/WHEEL
tinyecs-0.2.10.dist-info/entry_points.txt
tinyecs-0.2.10.dist-info/top_level.txt
tinyecs-0.2.10.dist-info/RECORD
