Metadata-Version: 2.4
Name: tinyecs
Version: 0.2.10
Summary: The teeniest, tiniest ECS system
Author-email: Michael Lamertz <michael.lamertz@gmail.com>
Project-URL: homepage, https://github.com/dickerdackel/tinyecs
Project-URL: bugtracker, https://github.com/DickerDackel/tinyecs/issues
Classifier: Development Status :: 3 - Alpha
Classifier: Intended Audience :: Developers
Classifier: License :: OSI Approved :: MIT License
Classifier: Topic :: Games/Entertainment
Classifier: Topic :: Software Development :: Libraries :: pygame
License-File: LICENSE
Requires-Dist: pgcooldown
Dynamic: license-file
